{
  "reel_id": "reel-YYYY02Feb 3, 2026063452",
  "date": "YYYY-02-Feb 3, 2026",
  "week_number": 9,
  "script": [
    "Devi walks toward the visible stage stairs with confident grace.",
    "Devi places her foot on the first step, beginning her ascent.",
    "Devi ascends the stairs step-by-step, the camera tracking her upward movement.",
    "The audience stands and applauds, their energy respectful and ceremonial.",
    "Devi reaches forward and receives the golden Grammy statuette on stage.",
    "Devi holds the Grammy, standing proudly as the soft light bloom emphasizes the moment."
  ],
  "caption": "A moment of recognition at the Grammy Awards. ✨🏆 #Grammy2026",
  "hashtags": "#Devi #GrammyAwards #Ceremony #GoldenMoment #AwardsSeason",
  "image_url": "https://github.com/ortall0201/social/raw/main/devi-videos/images/reel-YYYY02Feb 3, 2026063452.webp",
  "video_url": "https://github.com/ortall0201/social/raw/main/devi-videos/videos/reel-YYYY02Feb 3, 2026063452.mp4",
  "trending_insights": "As the lights dimmed, a figure clad in a strikingly tailored ensemble stepped onto the stage, each deliberate stride echoing the gravity of the moment. The fabric cascaded in an architectural silhouette, commanding attention and evoking a sense of both elegance and authority as the applause crescendoed, filling the room with palpable anticipation. The audience, captivated by the poised presence, erupted into cheers, the sound amplifying the weight of the recognition being bestowed. This moment t",
  "poll_attempts": 1,
  "status": "success"
}